odoo8_addon_partner_location_auto_create-8.0.0.1.0-py2.7-nspkg.pth
odoo_addons/partner_location_auto_create/__openerp__.py
odoo_addons/partner_location_auto_create/__init__.py
odoo_addons/partner_location_auto_create/README.rst
odoo_addons/partner_location_auto_create/models/res_partner.py
odoo_addons/partner_location_auto_create/models/stock_location.py
odoo_addons/partner_location_auto_create/models/__init__.py
odoo_addons/partner_location_auto_create/models/res_company.py
odoo_addons/partner_location_auto_create/i18n/it.po
odoo_addons/partner_location_auto_create/i18n/es.po
odoo_addons/partner_location_auto_create/i18n/sl.po
odoo_addons/partner_location_auto_create/i18n/nl.po
odoo_addons/partner_location_auto_create/i18n/de.po
odoo_addons/partner_location_auto_create/i18n/fr.po
odoo_addons/partner_location_auto_create/i18n/partner_location_auto_create.pot
odoo_addons/partner_location_auto_create/i18n/fi.po
odoo_addons/partner_location_auto_create/views/stock_location_view.xml
odoo_addons/partner_location_auto_create/views/res_partner_view.xml
odoo_addons/partner_location_auto_create/views/res_company_view.xml
odoo_addons/partner_location_auto_create/tests/__init__.py
odoo_addons/partner_location_auto_create/tests/test_res_partner.py
odoo8_addon_partner_location_auto_create-8.0.0.1.0.dist-info/top_level.txt
odoo8_addon_partner_location_auto_create-8.0.0.1.0.dist-info/WHEEL
odoo8_addon_partner_location_auto_create-8.0.0.1.0.dist-info/RECORD
odoo8_addon_partner_location_auto_create-8.0.0.1.0.dist-info/metadata.json
odoo8_addon_partner_location_auto_create-8.0.0.1.0.dist-info/DESCRIPTION.rst
odoo8_addon_partner_location_auto_create-8.0.0.1.0.dist-info/METADATA
odoo8_addon_partner_location_auto_create-8.0.0.1.0.dist-info/namespace_packages.txt
